{
  "rate": [
    { "timestamp": 1725583514, "count": 58 },
    { "timestamp": 1725583560, "count": 65 },
    { "timestamp": 1725583620, "count": 68 },
    { "timestamp": 1725583680, "count": 30 },
    { "timestamp": 1725583750, "count": 7 },
    { "timestamp": 1725583994, "count": 19 },
    { "timestamp": 1725584067, "count": 31 },
    { "timestamp": 1725584100, "count": 60 },
    { "timestamp": 1725584160, "count": 30 },
    { "timestamp": 1725584282, "count": 37 },
    { "timestamp": 1725584373, "count": 22 },
    { "timestamp": 1725584400, "count": 27 },
    { "timestamp": 1725584800, "count": 18 },
    { "timestamp": 1725584820, "count": 18 },
    { "timestamp": 1725585007, "count": 10 },
    { "timestamp": 1725585061, "count": 12 },
    { "timestamp": 1725585140, "count": 1 },
    { "timestamp": 1725605038, "count": 1 },
    { "timestamp": 1725605062, "count": 1 },
    { "timestamp": 1725606956, "count": 1 },
    { "timestamp": 1725606981, "count": 41 },
    { "timestamp": 1725607021, "count": 61 },
    { "timestamp": 1725607087, "count": 31 },
    { "timestamp": 1725607141, "count": 40 },
    { "timestamp": 1725607200, "count": 57 },
    { "timestamp": 1725607260, "count": 77 },
    { "timestamp": 1725607320, "count": 63 },
    { "timestamp": 1725607380, "count": 58 },
    { "timestamp": 1725607440, "count": 67 },
    { "timestamp": 1725607502, "count": 68 },
    { "timestamp": 1725607560, "count": 58 },
    { "timestamp": 1725607620, "count": 73 },
    { "timestamp": 1725607680, "count": 57 },
    { "timestamp": 1725607740, "count": 70 },
    { "timestamp": 1725607802, "count": 74 },
    { "timestamp": 1725607864, "count": 57 },
    { "timestamp": 1725607922, "count": 71 },
    { "timestamp": 1725607980, "count": 67 },
    { "timestamp": 1725608040, "count": 68 },
    { "timestamp": 1725608100, "count": 67 },
    { "timestamp": 1725608161, "count": 53 },
    { "timestamp": 1725608220, "count": 84 },
    { "timestamp": 1725608280, "count": 72 },
    { "timestamp": 1725608340, "count": 71 },
    { "timestamp": 1725608400, "count": 75 },
    { "timestamp": 1725608460, "count": 63 },
    { "timestamp": 1725608520, "count": 62 },
    { "timestamp": 1725608580, "count": 63 },
    { "timestamp": 1725608640, "count": 61 },
    { "timestamp": 1725608700, "count": 68 },
    { "timestamp": 1725608760, "count": 70 },
    { "timestamp": 1725608821, "count": 73 },
    { "timestamp": 1725608880, "count": 70 },
    { "timestamp": 1725608940, "count": 69 },
    { "timestamp": 1725609000, "count": 75 },
    { "timestamp": 1725609062, "count": 68 },
    { "timestamp": 1725609120, "count": 61 },
    { "timestamp": 1725609180, "count": 57 },
    { "timestamp": 1725609240, "count": 69 },
    { "timestamp": 1725609300, "count": 77 },
    { "timestamp": 1725609361, "count": 69 },
    { "timestamp": 1725609420, "count": 79 },
    { "timestamp": 1725609482, "count": 79 },
    { "timestamp": 1725609540, "count": 67 },
    { "timestamp": 1725609601, "count": 64 },
    { "timestamp": 1725609660, "count": 34 },
    { "timestamp": 1725609792, "count": 7 },
    { "timestamp": 1725609843, "count": 49 },
    { "timestamp": 1725609900, "count": 48 },
    { "timestamp": 1725609960, "count": 61 },
    { "timestamp": 1725610020, "count": 74 },
    { "timestamp": 1725610081, "count": 67 },
    { "timestamp": 1725610141, "count": 67 },
    { "timestamp": 1725610200, "count": 67 },
    { "timestamp": 1725610260, "count": 77 },
    { "timestamp": 1725610321, "count": 76 },
    { "timestamp": 1725610380, "count": 68 },
    { "timestamp": 1725610440, "count": 78 },
    { "timestamp": 1725610500, "count": 65 },
    { "timestamp": 1725610560, "count": 67 },
    { "timestamp": 1725610621, "count": 37 },
    { "timestamp": 1725610682, "count": 55 },
    { "timestamp": 1725610740, "count": 51 },
    { "timestamp": 1725610800, "count": 72 },
    { "timestamp": 1725610860, "count": 75 },
    { "timestamp": 1725610921, "count": 76 },
    { "timestamp": 1725610980, "count": 59 },
    { "timestamp": 1725611040, "count": 76 },
    { "timestamp": 1725611101, "count": 60 },
    { "timestamp": 1725611160, "count": 64 },
    { "timestamp": 1725611220, "count": 60 },
    { "timestamp": 1725611281, "count": 57 },
    { "timestamp": 1725611341, "count": 56 },
    { "timestamp": 1725611400, "count": 50 },
    { "timestamp": 1725611461, "count": 49 },
    { "timestamp": 1725611521, "count": 45 },
    { "timestamp": 1725611582, "count": 50 },
    { "timestamp": 1725611642, "count": 52 },
    { "timestamp": 1725611700, "count": 63 },
    { "timestamp": 1725611760, "count": 45 },
    { "timestamp": 1725611820, "count": 49 },
    { "timestamp": 1725611881, "count": 50 },
    { "timestamp": 1725611940, "count": 51 },
    { "timestamp": 1725612000, "count": 60 },
    { "timestamp": 1725612060, "count": 25 },
    { "timestamp": 1725612140, "count": 5 },
    { "timestamp": 1725612362, "count": 1 },
    { "timestamp": 1725612887, "count": 2 },
    { "timestamp": 1725613146, "count": 37 },
    { "timestamp": 1725613200, "count": 62 },
    { "timestamp": 1725613261, "count": 58 },
    { "timestamp": 1725613321, "count": 66 },
    { "timestamp": 1725613382, "count": 58 },
    { "timestamp": 1725613440, "count": 66 },
    { "timestamp": 1725613500, "count": 68 },
    { "timestamp": 1725613561, "count": 53 },
    { "timestamp": 1725613620, "count": 55 },
    { "timestamp": 1725613680, "count": 51 },
    { "timestamp": 1725613741, "count": 50 },
    { "timestamp": 1725613800, "count": 59 },
    { "timestamp": 1725613861, "count": 62 },
    { "timestamp": 1725613921, "count": 65 },
    { "timestamp": 1725613980, "count": 73 },
    { "timestamp": 1725614041, "count": 69 },
    { "timestamp": 1725614100, "count": 67 },
    { "timestamp": 1725614160, "count": 70 },
    { "timestamp": 1725614220, "count": 79 },
    { "timestamp": 1725614280, "count": 60 },
    { "timestamp": 1725614340, "count": 61 },
    { "timestamp": 1725614401, "count": 46 },
    { "timestamp": 1725614460, "count": 54 },
    { "timestamp": 1725614522, "count": 55 },
    { "timestamp": 1725614580, "count": 58 },
    { "timestamp": 1725614640, "count": 46 },
    { "timestamp": 1725614700, "count": 50 },
    { "timestamp": 1725614760, "count": 70 },
    { "timestamp": 1725614820, "count": 54 },
    { "timestamp": 1725614880, "count": 50 },
    { "timestamp": 1725614940, "count": 66 },
    { "timestamp": 1725615001, "count": 50 },
    { "timestamp": 1725615062, "count": 55 },
    { "timestamp": 1725615120, "count": 35 },
    { "timestamp": 1725615180, "count": 44 },
    { "timestamp": 1725615241, "count": 63 },
    { "timestamp": 1725615300, "count": 53 },
    { "timestamp": 1725615360, "count": 51 },
    { "timestamp": 1725615420, "count": 59 },
    { "timestamp": 1725615480, "count": 62 },
    { "timestamp": 1725615540, "count": 73 },
    { "timestamp": 1725615600, "count": 64 },
    { "timestamp": 1725615660, "count": 57 },
    { "timestamp": 1725615720, "count": 60 },
    { "timestamp": 1725615780, "count": 64 },
    { "timestamp": 1725615840, "count": 54 },
    { "timestamp": 1725615900, "count": 44 },
    { "timestamp": 1725615960, "count": 28 },
    { "timestamp": 1725616021, "count": 49 },
    { "timestamp": 1725616082, "count": 39 },
    { "timestamp": 1725616144, "count": 34 },
    { "timestamp": 1725616205, "count": 42 },
    { "timestamp": 1725616263, "count": 65 },
    { "timestamp": 1725616322, "count": 64 },
    { "timestamp": 1725616380, "count": 59 },
    { "timestamp": 1725616440, "count": 53 },
    { "timestamp": 1725616500, "count": 46 },
    { "timestamp": 1725616560, "count": 38 },
    { "timestamp": 1725616626, "count": 48 },
    { "timestamp": 1725616687, "count": 55 },
    { "timestamp": 1725616740, "count": 58 },
    { "timestamp": 1725616800, "count": 58 },
    { "timestamp": 1725616860, "count": 72 },
    { "timestamp": 1725616920, "count": 66 },
    { "timestamp": 1725616980, "count": 62 },
    { "timestamp": 1725617040, "count": 69 },
    { "timestamp": 1725617103, "count": 61 },
    { "timestamp": 1725617161, "count": 56 },
    { "timestamp": 1725617220, "count": 35 },
    { "timestamp": 1725617292, "count": 11 },
    { "timestamp": 1725617340, "count": 57 },
    { "timestamp": 1725617400, "count": 60 },
    { "timestamp": 1725617460, "count": 68 },
    { "timestamp": 1725617520, "count": 70 },
    { "timestamp": 1725617583, "count": 67 },
    { "timestamp": 1725617640, "count": 53 },
    { "timestamp": 1725617701, "count": 53 },
    { "timestamp": 1725617760, "count": 60 },
    { "timestamp": 1725617822, "count": 58 },
    { "timestamp": 1725617880, "count": 58 },
    { "timestamp": 1725617940, "count": 66 },
    { "timestamp": 1725618000, "count": 64 },
    { "timestamp": 1725618060, "count": 67 },
    { "timestamp": 1725618120, "count": 62 },
    { "timestamp": 1725618182, "count": 28 },
    { "timestamp": 1725618242, "count": 57 },
    { "timestamp": 1725618300, "count": 60 },
    { "timestamp": 1725618362, "count": 60 },
    { "timestamp": 1725618420, "count": 61 },
    { "timestamp": 1725618483, "count": 48 },
    { "timestamp": 1725618540, "count": 49 },
    { "timestamp": 1725618600, "count": 58 },
    { "timestamp": 1725618660, "count": 43 },
    { "timestamp": 1725618721, "count": 17 },
    { "timestamp": 1725618794, "count": 4 },
    { "timestamp": 1725618887, "count": 10 },
    { "timestamp": 1725618900, "count": 35 },
    { "timestamp": 1725618960, "count": 39 },
    { "timestamp": 1725619020, "count": 45 },
    { "timestamp": 1725619085, "count": 55 },
    { "timestamp": 1725619141, "count": 13 },
    { "timestamp": 1725619201, "count": 21 },
    { "timestamp": 1725619261, "count": 50 },
    { "timestamp": 1725619321, "count": 39 },
    { "timestamp": 1725619380, "count": 43 },
    { "timestamp": 1725619446, "count": 42 },
    { "timestamp": 1725619521, "count": 8 },
    { "timestamp": 1725619562, "count": 12 },
    { "timestamp": 1725619621, "count": 1 },
    { "timestamp": 1725619796, "count": 2 },
    { "timestamp": 1725620583, "count": 2 },
    { "timestamp": 1725621012, "count": 15 },
    { "timestamp": 1725621063, "count": 17 },
    { "timestamp": 1725621727, "count": 10 },
    { "timestamp": 1725621784, "count": 13 },
    { "timestamp": 1725621853, "count": 5 },
    { "timestamp": 1725621909, "count": 29 },
    { "timestamp": 1725621960, "count": 69 },
    { "timestamp": 1725622020, "count": 63 },
    { "timestamp": 1725622080, "count": 47 },
    { "timestamp": 1725622140, "count": 66 },
    { "timestamp": 1725622200, "count": 78 },
    { "timestamp": 1725622260, "count": 69 },
    { "timestamp": 1725622320, "count": 72 },
    { "timestamp": 1725622380, "count": 74 },
    { "timestamp": 1725622440, "count": 77 },
    { "timestamp": 1725622502, "count": 45 },
    { "timestamp": 1725622561, "count": 41 },
    { "timestamp": 1725622623, "count": 41 },
    { "timestamp": 1725622680, "count": 62 },
    { "timestamp": 1725622742, "count": 56 },
    { "timestamp": 1725622800, "count": 66 },
    { "timestamp": 1725622860, "count": 66 },
    { "timestamp": 1725622921, "count": 69 },
    { "timestamp": 1725622981, "count": 70 },
    { "timestamp": 1725623040, "count": 75 },
    { "timestamp": 1725623100, "count": 68 },
    { "timestamp": 1725623160, "count": 50 },
    { "timestamp": 1725623220, "count": 69 },
    { "timestamp": 1725623280, "count": 75 },
    { "timestamp": 1725623340, "count": 69 },
    { "timestamp": 1725623400, "count": 67 },
    { "timestamp": 1725623462, "count": 73 },
    { "timestamp": 1725623520, "count": 74 },
    { "timestamp": 1725623580, "count": 50 },
    { "timestamp": 1725623640, "count": 53 },
    { "timestamp": 1725623700, "count": 70 },
    { "timestamp": 1725623761, "count": 59 },
    { "timestamp": 1725623820, "count": 67 },
    { "timestamp": 1725623880, "count": 62 },
    { "timestamp": 1725623940, "count": 63 },
    { "timestamp": 1725624000, "count": 63 },
    { "timestamp": 1725624061, "count": 71 },
    { "timestamp": 1725624120, "count": 60 },
    { "timestamp": 1725624181, "count": 59 },
    { "timestamp": 1725624240, "count": 64 },
    { "timestamp": 1725624302, "count": 73 },
    { "timestamp": 1725624360, "count": 65 },
    { "timestamp": 1725624421, "count": 57 },
    { "timestamp": 1725624486, "count": 64 },
    { "timestamp": 1725624540, "count": 66 },
    { "timestamp": 1725624601, "count": 45 },
    { "timestamp": 1725624660, "count": 30 },
    { "timestamp": 1725624720, "count": 69 },
    { "timestamp": 1725624780, "count": 51 },
    { "timestamp": 1725624840, "count": 55 },
    { "timestamp": 1725624900, "count": 57 },
    { "timestamp": 1725624961, "count": 48 },
    { "timestamp": 1725625020, "count": 71 },
    { "timestamp": 1725625081, "count": 61 },
    { "timestamp": 1725625140, "count": 71 },
    { "timestamp": 1725625200, "count": 74 },
    { "timestamp": 1725625260, "count": 64 },
    { "timestamp": 1725625320, "count": 54 },
    { "timestamp": 1725625380, "count": 76 },
    { "timestamp": 1725625440, "count": 69 },
    { "timestamp": 1725625501, "count": 69 },
    { "timestamp": 1725625560, "count": 56 },
    { "timestamp": 1725625621, "count": 33 },
    { "timestamp": 1725625681, "count": 36 },
    { "timestamp": 1725625740, "count": 46 },
    { "timestamp": 1725625807, "count": 46 },
    { "timestamp": 1725625860, "count": 49 },
    { "timestamp": 1725625921, "count": 33 },
    { "timestamp": 1725625987, "count": 28 },
    { "timestamp": 1725626043, "count": 51 },
    { "timestamp": 1725626100, "count": 77 },
    { "timestamp": 1725626160, "count": 56 },
    { "timestamp": 1725626220, "count": 80 },
    { "timestamp": 1725626280, "count": 56 },
    { "timestamp": 1725626340, "count": 58 },
    { "timestamp": 1725626400, "count": 70 },
    { "timestamp": 1725626460, "count": 52 },
    { "timestamp": 1725626521, "count": 39 },
    { "timestamp": 1725626580, "count": 40 },
    { "timestamp": 1725626640, "count": 31 },
    { "timestamp": 1725626700, "count": 48 },
    { "timestamp": 1725626760, "count": 60 },
    { "timestamp": 1725626821, "count": 57 },
    { "timestamp": 1725626880, "count": 73 },
    { "timestamp": 1725626940, "count": 50 },
    { "timestamp": 1725627001, "count": 63 },
    { "timestamp": 1725627061, "count": 62 },
    { "timestamp": 1725627120, "count": 32 },
    { "timestamp": 1725627180, "count": 63 },
    { "timestamp": 1725627240, "count": 52 },
    { "timestamp": 1725627306, "count": 65 },
    { "timestamp": 1725627360, "count": 42 },
    { "timestamp": 1725627421, "count": 77 },
    { "timestamp": 1725627481, "count": 63 },
    { "timestamp": 1725627541, "count": 70 },
    { "timestamp": 1725627600, "count": 44 },
    { "timestamp": 1725627660, "count": 44 },
    { "timestamp": 1725627720, "count": 33 },
    { "timestamp": 1725627781, "count": 27 },
    { "timestamp": 1725627840, "count": 48 },
    { "timestamp": 1725627904, "count": 29 },
    { "timestamp": 1725627960, "count": 44 },
    { "timestamp": 1725628020, "count": 41 },
    { "timestamp": 1725628080, "count": 48 },
    { "timestamp": 1725628140, "count": 48 },
    { "timestamp": 1725628200, "count": 45 },
    { "timestamp": 1725628270, "count": 32 },
    { "timestamp": 1725628321, "count": 26 },
    { "timestamp": 1725628381, "count": 39 },
    { "timestamp": 1725628440, "count": 33 },
    { "timestamp": 1725628500, "count": 21 },
    { "timestamp": 1725628560, "count": 3 },
    { "timestamp": 1725629480, "count": 26 },
    { "timestamp": 1725629548, "count": 14 },
    { "timestamp": 1725629582, "count": 53 },
    { "timestamp": 1725629641, "count": 25 },
    { "timestamp": 1725629700, "count": 53 },
    { "timestamp": 1725629760, "count": 54 },
    { "timestamp": 1725629820, "count": 40 },
    { "timestamp": 1725629881, "count": 63 },
    { "timestamp": 1725629940, "count": 41 },
    { "timestamp": 1725630000, "count": 28 },
    { "timestamp": 1725630083, "count": 29 },
    { "timestamp": 1725630121, "count": 37 },
    { "timestamp": 1725630181, "count": 49 },
    { "timestamp": 1725630240, "count": 46 },
    { "timestamp": 1725630308, "count": 41 },
    { "timestamp": 1725630361, "count": 36 },
    { "timestamp": 1725630441, "count": 45 },
    { "timestamp": 1725630480, "count": 46 },
    { "timestamp": 1725630560, "count": 40 },
    { "timestamp": 1725630627, "count": 23 },
    { "timestamp": 1725630660, "count": 54 },
    { "timestamp": 1725630722, "count": 35 },
    { "timestamp": 1725630793, "count": 42 },
    { "timestamp": 1725630840, "count": 36 },
    { "timestamp": 1725630900, "count": 56 },
    { "timestamp": 1725630960, "count": 61 },
    { "timestamp": 1725631021, "count": 39 },
    { "timestamp": 1725631080, "count": 40 },
    { "timestamp": 1725631151, "count": 42 },
    { "timestamp": 1725631201, "count": 42 },
    { "timestamp": 1725631269, "count": 43 },
    { "timestamp": 1725631320, "count": 35 },
    { "timestamp": 1725631380, "count": 66 },
    { "timestamp": 1725631440, "count": 72 },
    { "timestamp": 1725631500, "count": 66 },
    { "timestamp": 1725631561, "count": 52 },
    { "timestamp": 1725631622, "count": 39 },
    { "timestamp": 1725631680, "count": 51 },
    { "timestamp": 1725631740, "count": 53 },
    { "timestamp": 1725631804, "count": 51 },
    { "timestamp": 1725631860, "count": 53 },
    { "timestamp": 1725631920, "count": 43 },
    { "timestamp": 1725631980, "count": 64 },
    { "timestamp": 1725632041, "count": 54 },
    { "timestamp": 1725632100, "count": 52 },
    { "timestamp": 1725632162, "count": 50 },
    { "timestamp": 1725632222, "count": 40 },
    { "timestamp": 1725632280, "count": 68 },
    { "timestamp": 1725632340, "count": 52 },
    { "timestamp": 1725632400, "count": 32 },
    { "timestamp": 1725632461, "count": 53 },
    { "timestamp": 1725632522, "count": 65 },
    { "timestamp": 1725632580, "count": 71 },
    { "timestamp": 1725632640, "count": 53 },
    { "timestamp": 1725632700, "count": 45 },
    { "timestamp": 1725632773, "count": 48 },
    { "timestamp": 1725632822, "count": 46 },
    { "timestamp": 1725632881, "count": 52 },
    { "timestamp": 1725632940, "count": 50 },
    { "timestamp": 1725633000, "count": 44 },
    { "timestamp": 1725633060, "count": 51 },
    { "timestamp": 1725633120, "count": 41 },
    { "timestamp": 1725633184, "count": 62 },
    { "timestamp": 1725633240, "count": 55 },
    { "timestamp": 1725633300, "count": 65 },
    { "timestamp": 1725633362, "count": 66 },
    { "timestamp": 1725633420, "count": 61 },
    { "timestamp": 1725633481, "count": 66 },
    { "timestamp": 1725633540, "count": 58 },
    { "timestamp": 1725633601, "count": 32 },
    { "timestamp": 1725633663, "count": 40 },
    { "timestamp": 1725633721, "count": 42 },
    { "timestamp": 1725633780, "count": 37 },
    { "timestamp": 1725633840, "count": 41 },
    { "timestamp": 1725633900, "count": 56 },
    { "timestamp": 1725633971, "count": 43 },
    { "timestamp": 1725634022, "count": 77 },
    { "timestamp": 1725634080, "count": 57 },
    { "timestamp": 1725634140, "count": 60 },
    { "timestamp": 1725634200, "count": 69 },
    { "timestamp": 1725634260, "count": 76 },
    { "timestamp": 1725634320, "count": 71 },
    { "timestamp": 1725634380, "count": 63 },
    { "timestamp": 1725634440, "count": 54 },
    { "timestamp": 1725634501, "count": 69 },
    { "timestamp": 1725634560, "count": 31 },
    { "timestamp": 1725634622, "count": 49 },
    { "timestamp": 1725634681, "count": 61 },
    { "timestamp": 1725634740, "count": 63 },
    { "timestamp": 1725634802, "count": 61 },
    { "timestamp": 1725634860, "count": 74 },
    { "timestamp": 1725634920, "count": 76 },
    { "timestamp": 1725634980, "count": 64 },
    { "timestamp": 1725635040, "count": 57 },
    { "timestamp": 1725635101, "count": 44 },
    { "timestamp": 1725635160, "count": 69 },
    { "timestamp": 1725635220, "count": 73 },
    { "timestamp": 1725635282, "count": 70 },
    { "timestamp": 1725635340, "count": 60 },
    { "timestamp": 1725635403, "count": 43 },
    { "timestamp": 1725635460, "count": 41 },
    { "timestamp": 1725635521, "count": 37 },
    { "timestamp": 1725635580, "count": 65 },
    { "timestamp": 1725635641, "count": 11 },
    { "timestamp": 1725635729, "count": 1 },
    { "timestamp": 1725635781, "count": 24 },
    { "timestamp": 1725635820, "count": 51 },
    { "timestamp": 1725635882, "count": 41 },
    { "timestamp": 1725635940, "count": 72 },
    { "timestamp": 1725636000, "count": 58 },
    { "timestamp": 1725636061, "count": 57 },
    { "timestamp": 1725636121, "count": 54 },
    { "timestamp": 1725636189, "count": 48 },
    { "timestamp": 1725636794, "count": 27 },
    { "timestamp": 1725636840, "count": 41 },
    { "timestamp": 1725636901, "count": 1 },
    { "timestamp": 1725637002, "count": 2 },
    { "timestamp": 1725637137, "count": 1 },
    { "timestamp": 1725637156, "count": 3 },
    { "timestamp": 1725637237, "count": 11 },
    { "timestamp": 1725637260, "count": 43 },
    { "timestamp": 1725637321, "count": 69 },
    { "timestamp": 1725637380, "count": 63 },
    { "timestamp": 1725637440, "count": 75 },
    { "timestamp": 1725637500, "count": 79 },
    { "timestamp": 1725637560, "count": 71 },
    { "timestamp": 1725637620, "count": 54 },
    { "timestamp": 1725637680, "count": 69 },
    { "timestamp": 1725637740, "count": 60 },
    { "timestamp": 1725637800, "count": 73 },
    { "timestamp": 1725637860, "count": 64 },
    { "timestamp": 1725637920, "count": 56 },
    { "timestamp": 1725637980, "count": 51 },
    { "timestamp": 1725638040, "count": 38 },
    { "timestamp": 1725638100, "count": 29 },
    { "timestamp": 1725638160, "count": 48 },
    { "timestamp": 1725638220, "count": 46 },
    { "timestamp": 1725638280, "count": 43 },
    { "timestamp": 1725638343, "count": 12 },
    { "timestamp": 1725638402, "count": 32 },
    { "timestamp": 1725638462, "count": 26 },
    { "timestamp": 1725638520, "count": 59 },
    { "timestamp": 1725638580, "count": 45 },
    { "timestamp": 1725638641, "count": 56 },
    { "timestamp": 1725638701, "count": 75 },
    { "timestamp": 1725638760, "count": 51 },
    { "timestamp": 1725638822, "count": 53 },
    { "timestamp": 1725638880, "count": 79 },
    { "timestamp": 1725638940, "count": 59 },
    { "timestamp": 1725639000, "count": 51 },
    { "timestamp": 1725639060, "count": 69 },
    { "timestamp": 1725639121, "count": 72 },
    { "timestamp": 1725639180, "count": 74 },
    { "timestamp": 1725639240, "count": 70 },
    { "timestamp": 1725639300, "count": 78 },
    { "timestamp": 1725639360, "count": 77 },
    { "timestamp": 1725639421, "count": 60 },
    { "timestamp": 1725639480, "count": 77 },
    { "timestamp": 1725639540, "count": 68 },
    { "timestamp": 1725639600, "count": 61 },
    { "timestamp": 1725639660, "count": 58 },
    { "timestamp": 1725639720, "count": 52 },
    { "timestamp": 1725639781, "count": 57 },
    { "timestamp": 1725639840, "count": 62 },
    { "timestamp": 1725639900, "count": 44 },
    { "timestamp": 1725639961, "count": 75 },
    { "timestamp": 1725640024, "count": 50 },
    { "timestamp": 1725640080, "count": 70 },
    { "timestamp": 1725640143, "count": 29 },
    { "timestamp": 1725640204, "count": 42 },
    { "timestamp": 1725640260, "count": 29 },
    { "timestamp": 1725640320, "count": 53 },
    { "timestamp": 1725640380, "count": 50 },
    { "timestamp": 1725640440, "count": 36 },
    { "timestamp": 1725640500, "count": 54 },
    { "timestamp": 1725640560, "count": 57 },
    { "timestamp": 1725640620, "count": 31 },
    { "timestamp": 1725640680, "count": 39 },
    { "timestamp": 1725640742, "count": 32 },
    { "timestamp": 1725640800, "count": 47 },
    { "timestamp": 1725640860, "count": 42 },
    { "timestamp": 1725640920, "count": 47 },
    { "timestamp": 1725640980, "count": 47 },
    { "timestamp": 1725641042, "count": 56 },
    { "timestamp": 1725641104, "count": 50 },
    { "timestamp": 1725641160, "count": 50 },
    { "timestamp": 1725641220, "count": 51 },
    { "timestamp": 1725641280, "count": 60 },
    { "timestamp": 1725641340, "count": 49 },
    { "timestamp": 1725641400, "count": 53 },
    { "timestamp": 1725641460, "count": 51 },
    { "timestamp": 1725641520, "count": 79 },
    { "timestamp": 1725641580, "count": 53 },
    { "timestamp": 1725641642, "count": 53 },
    { "timestamp": 1725641700, "count": 56 },
    { "timestamp": 1725641762, "count": 59 },
    { "timestamp": 1725641820, "count": 58 },
    { "timestamp": 1725641880, "count": 42 },
    { "timestamp": 1725641941, "count": 51 },
    { "timestamp": 1725642001, "count": 60 },
    { "timestamp": 1725642060, "count": 62 },
    { "timestamp": 1725642120, "count": 74 },
    { "timestamp": 1725642180, "count": 66 },
    { "timestamp": 1725642240, "count": 66 },
    { "timestamp": 1725642300, "count": 73 },
    { "timestamp": 1725642360, "count": 64 },
    { "timestamp": 1725642420, "count": 64 },
    { "timestamp": 1725642480, "count": 40 },
    { "timestamp": 1725642540, "count": 47 },
    { "timestamp": 1725642600, "count": 48 },
    { "timestamp": 1725642660, "count": 38 },
    { "timestamp": 1725642723, "count": 13 },
    { "timestamp": 1725642835, "count": 4 },
    { "timestamp": 1725642840, "count": 48 },
    { "timestamp": 1725642974, "count": 14 },
    { "timestamp": 1725643035, "count": 1 },
    { "timestamp": 1725643682, "count": 2 },
    { "timestamp": 1725643777, "count": 6 },
    { "timestamp": 1725643828, "count": 1 },
    { "timestamp": 1725643866, "count": 14 },
    { "timestamp": 1725643922, "count": 34 },
    { "timestamp": 1725643981, "count": 42 },
    { "timestamp": 1725644040, "count": 49 },
    { "timestamp": 1725644104, "count": 44 },
    { "timestamp": 1725644160, "count": 58 },
    { "timestamp": 1725644224, "count": 38 },
    { "timestamp": 1725644281, "count": 38 },
    { "timestamp": 1725644340, "count": 62 },
    { "timestamp": 1725644400, "count": 60 },
    { "timestamp": 1725644461, "count": 48 },
    { "timestamp": 1725644524, "count": 55 },
    { "timestamp": 1725644580, "count": 45 },
    { "timestamp": 1725644640, "count": 43 },
    { "timestamp": 1725644702, "count": 44 },
    { "timestamp": 1725644760, "count": 50 },
    { "timestamp": 1725644822, "count": 43 },
    { "timestamp": 1725644880, "count": 50 },
    { "timestamp": 1725644940, "count": 40 },
    { "timestamp": 1725645006, "count": 28 },
    { "timestamp": 1725645060, "count": 67 },
    { "timestamp": 1725645120, "count": 43 },
    { "timestamp": 1725645180, "count": 33 },
    { "timestamp": 1725645241, "count": 34 },
    { "timestamp": 1725645306, "count": 55 },
    { "timestamp": 1725645362, "count": 61 },
    { "timestamp": 1725645421, "count": 65 },
    { "timestamp": 1725645480, "count": 53 },
    { "timestamp": 1725645541, "count": 51 },
    { "timestamp": 1725645600, "count": 45 },
    { "timestamp": 1725645660, "count": 62 },
    { "timestamp": 1725645720, "count": 53 },
    { "timestamp": 1725645780, "count": 61 },
    { "timestamp": 1725645841, "count": 52 },
    { "timestamp": 1725645902, "count": 32 },
    { "timestamp": 1725645960, "count": 62 },
    { "timestamp": 1725646020, "count": 40 },
    { "timestamp": 1725646080, "count": 52 },
    { "timestamp": 1725646145, "count": 57 },
    { "timestamp": 1725646201, "count": 46 },
    { "timestamp": 1725646260, "count": 55 },
    { "timestamp": 1725646327, "count": 39 },
    { "timestamp": 1725646382, "count": 32 },
    { "timestamp": 1725646441, "count": 38 },
    { "timestamp": 1725646500, "count": 38 },
    { "timestamp": 1725646561, "count": 54 },
    { "timestamp": 1725646621, "count": 57 },
    { "timestamp": 1725646681, "count": 52 },
    { "timestamp": 1725646741, "count": 58 },
    { "timestamp": 1725646804, "count": 55 },
    { "timestamp": 1725646861, "count": 66 },
    { "timestamp": 1725646920, "count": 53 },
    { "timestamp": 1725646980, "count": 50 },
    { "timestamp": 1725647040, "count": 57 },
    { "timestamp": 1725647100, "count": 51 },
    { "timestamp": 1725647160, "count": 60 },
    { "timestamp": 1725647220, "count": 64 },
    { "timestamp": 1725647280, "count": 73 },
    { "timestamp": 1725647340, "count": 58 },
    { "timestamp": 1725647400, "count": 61 },
    { "timestamp": 1725647462, "count": 67 },
    { "timestamp": 1725647520, "count": 61 },
    { "timestamp": 1725647580, "count": 65 },
    { "timestamp": 1725647643, "count": 44 },
    { "timestamp": 1725647700, "count": 53 },
    { "timestamp": 1725647761, "count": 49 },
    { "timestamp": 1725647820, "count": 59 },
    { "timestamp": 1725647880, "count": 53 },
    { "timestamp": 1725647940, "count": 44 },
    { "timestamp": 1725648002, "count": 53 },
    { "timestamp": 1725648060, "count": 55 },
    { "timestamp": 1725648120, "count": 50 },
    { "timestamp": 1725648180, "count": 63 },
    { "timestamp": 1725648241, "count": 64 },
    { "timestamp": 1725648302, "count": 41 },
    { "timestamp": 1725648361, "count": 39 },
    { "timestamp": 1725648420, "count": 46 },
    { "timestamp": 1725648481, "count": 65 },
    { "timestamp": 1725648540, "count": 64 },
    { "timestamp": 1725648600, "count": 43 },
    { "timestamp": 1725648661, "count": 47 },
    { "timestamp": 1725648720, "count": 46 },
    { "timestamp": 1725648780, "count": 52 },
    { "timestamp": 1725648840, "count": 36 },
    { "timestamp": 1725648900, "count": 39 },
    { "timestamp": 1725648961, "count": 55 },
    { "timestamp": 1725649021, "count": 48 },
    { "timestamp": 1725649080, "count": 58 },
    { "timestamp": 1725649141, "count": 52 },
    { "timestamp": 1725649200, "count": 57 },
    { "timestamp": 1725649261, "count": 67 },
    { "timestamp": 1725649320, "count": 59 },
    { "timestamp": 1725649380, "count": 60 },
    { "timestamp": 1725649440, "count": 70 },
    { "timestamp": 1725649501, "count": 64 },
    { "timestamp": 1725649561, "count": 65 },
    { "timestamp": 1725649620, "count": 61 },
    { "timestamp": 1725649680, "count": 59 },
    { "timestamp": 1725649740, "count": 38 },
    { "timestamp": 1725649800, "count": 19 },
    { "timestamp": 1725649861, "count": 5 },
    { "timestamp": 1725649927, "count": 28 },
    { "timestamp": 1725649980, "count": 52 },
    { "timestamp": 1725650055, "count": 14 },
    { "timestamp": 1725650109, "count": 2 },
    { "timestamp": 1725650257, "count": 1 },
    { "timestamp": 1725650402, "count": 1 },
    { "timestamp": 1725652106, "count": 10 },
    { "timestamp": 1725652142, "count": 7 },
    { "timestamp": 1725652204, "count": 9 },
    { "timestamp": 1725652307, "count": 7 },
    { "timestamp": 1725652320, "count": 49 },
    { "timestamp": 1725652380, "count": 74 },
    { "timestamp": 1725652440, "count": 63 },
    { "timestamp": 1725652501, "count": 68 },
    { "timestamp": 1725652560, "count": 59 },
    { "timestamp": 1725652620, "count": 45 },
    { "timestamp": 1725652680, "count": 57 },
    { "timestamp": 1725652740, "count": 61 },
    { "timestamp": 1725652800, "count": 59 },
    { "timestamp": 1725652860, "count": 60 },
    { "timestamp": 1725652922, "count": 58 },
    { "timestamp": 1725652980, "count": 66 },
    { "timestamp": 1725653040, "count": 62 },
    { "timestamp": 1725653100, "count": 48 },
    { "timestamp": 1725653160, "count": 49 },
    { "timestamp": 1725653220, "count": 60 },
    { "timestamp": 1725653281, "count": 63 },
    { "timestamp": 1725653341, "count": 45 },
    { "timestamp": 1725653401, "count": 49 },
    { "timestamp": 1725653461, "count": 41 },
    { "timestamp": 1725653521, "count": 58 },
    { "timestamp": 1725653594, "count": 26 },
    { "timestamp": 1725653644, "count": 47 },
    { "timestamp": 1725653701, "count": 63 },
    { "timestamp": 1725653760, "count": 46 },
    { "timestamp": 1725653820, "count": 61 },
    { "timestamp": 1725653881, "count": 63 },
    { "timestamp": 1725653941, "count": 65 },
    { "timestamp": 1725654000, "count": 56 },
    { "timestamp": 1725654060, "count": 65 },
    { "timestamp": 1725654120, "count": 56 },
    { "timestamp": 1725654180, "count": 65 },
    { "timestamp": 1725654240, "count": 67 },
    { "timestamp": 1725654300, "count": 64 },
    { "timestamp": 1725654360, "count": 67 },
    { "timestamp": 1725654422, "count": 46 },
    { "timestamp": 1725654481, "count": 64 },
    { "timestamp": 1725654540, "count": 64 },
    { "timestamp": 1725654601, "count": 41 },
    { "timestamp": 1725654660, "count": 65 },
    { "timestamp": 1725654720, "count": 52 },
    { "timestamp": 1725654780, "count": 56 },
    { "timestamp": 1725654840, "count": 48 },
    { "timestamp": 1725654902, "count": 47 },
    { "timestamp": 1725654961, "count": 53 },
    { "timestamp": 1725655020, "count": 62 },
    { "timestamp": 1725655080, "count": 48 },
    { "timestamp": 1725655141, "count": 52 },
    { "timestamp": 1725655200, "count": 65 },
    { "timestamp": 1725655260, "count": 57 },
    { "timestamp": 1725655320, "count": 61 },
    { "timestamp": 1725655380, "count": 60 },
    { "timestamp": 1725655440, "count": 64 },
    { "timestamp": 1725655500, "count": 45 },
    { "timestamp": 1725655560, "count": 50 },
    { "timestamp": 1725655623, "count": 50 },
    { "timestamp": 1725655680, "count": 53 },
    { "timestamp": 1725655740, "count": 58 },
    { "timestamp": 1725655800, "count": 65 },
    { "timestamp": 1725655870, "count": 28 },
    { "timestamp": 1725655920, "count": 32 },
    { "timestamp": 1725655980, "count": 48 },
    { "timestamp": 1725656040, "count": 57 },
    { "timestamp": 1725656100, "count": 52 },
    { "timestamp": 1725656160, "count": 52 },
    { "timestamp": 1725656220, "count": 51 },
    { "timestamp": 1725656281, "count": 43 },
    { "timestamp": 1725656340, "count": 48 },
    { "timestamp": 1725656400, "count": 61 },
    { "timestamp": 1725656460, "count": 63 },
    { "timestamp": 1725656520, "count": 70 },
    { "timestamp": 1725656582, "count": 59 },
    { "timestamp": 1725656640, "count": 62 },
    { "timestamp": 1725656702, "count": 62 },
    { "timestamp": 1725656762, "count": 56 },
    { "timestamp": 1725656820, "count": 61 },
    { "timestamp": 1725656880, "count": 54 },
    { "timestamp": 1725656941, "count": 49 },
    { "timestamp": 1725657000, "count": 52 },
    { "timestamp": 1725657062, "count": 48 },
    { "timestamp": 1725657122, "count": 46 },
    { "timestamp": 1725657180, "count": 36 },
    { "timestamp": 1725657240, "count": 48 },
    { "timestamp": 1725657304, "count": 44 },
    { "timestamp": 1725657360, "count": 44 },
    { "timestamp": 1725657424, "count": 33 },
    { "timestamp": 1725657480, "count": 50 },
    { "timestamp": 1725657540, "count": 43 },
    { "timestamp": 1725657602, "count": 13 },
    { "timestamp": 1725657673, "count": 46 },
    { "timestamp": 1725657720, "count": 60 },
    { "timestamp": 1725657782, "count": 58 },
    { "timestamp": 1725657840, "count": 49 },
    { "timestamp": 1725657900, "count": 74 },
    { "timestamp": 1725657960, "count": 71 },
    { "timestamp": 1725658020, "count": 27 },
    { "timestamp": 1725658083, "count": 41 },
    { "timestamp": 1725658140, "count": 63 },
    { "timestamp": 1725658200, "count": 52 },
    { "timestamp": 1725658260, "count": 44 },
    { "timestamp": 1725658321, "count": 40 },
    { "timestamp": 1725658380, "count": 44 },
    { "timestamp": 1725658441, "count": 38 },
    { "timestamp": 1725658502, "count": 49 },
    { "timestamp": 1725658560, "count": 49 },
    { "timestamp": 1725658620, "count": 37 },
    { "timestamp": 1725658680, "count": 57 },
    { "timestamp": 1725658740, "count": 32 },
    { "timestamp": 1725658816, "count": 38 },
    { "timestamp": 1725658862, "count": 44 },
    { "timestamp": 1725658920, "count": 50 },
    { "timestamp": 1725658980, "count": 40 },
    { "timestamp": 1725659042, "count": 27 },
    { "timestamp": 1725659103, "count": 26 },
    { "timestamp": 1725659163, "count": 33 },
    { "timestamp": 1725659220, "count": 34 },
    { "timestamp": 1725659280, "count": 32 },
    { "timestamp": 1725659340, "count": 56 },
    { "timestamp": 1725659400, "count": 53 },
    { "timestamp": 1725659460, "count": 63 },
    { "timestamp": 1725659520, "count": 22 },
    { "timestamp": 1725659580, "count": 7 },
    { "timestamp": 1725659640, "count": 24 },
    { "timestamp": 1725660331, "count": 23 },
    { "timestamp": 1725660360, "count": 32 },
    { "timestamp": 1725660557, "count": 10 },
    { "timestamp": 1725660601, "count": 9 },
    { "timestamp": 1725660660, "count": 56 },
    { "timestamp": 1725660720, "count": 62 },
    { "timestamp": 1725660780, "count": 64 },
    { "timestamp": 1725660840, "count": 58 },
    { "timestamp": 1725660900, "count": 40 },
    { "timestamp": 1725660960, "count": 65 },
    { "timestamp": 1725661020, "count": 59 },
    { "timestamp": 1725661080, "count": 60 },
    { "timestamp": 1725661141, "count": 63 },
    { "timestamp": 1725661200, "count": 68 },
    { "timestamp": 1725661260, "count": 57 },
    { "timestamp": 1725661320, "count": 62 },
    { "timestamp": 1725661381, "count": 56 },
    { "timestamp": 1725661440, "count": 60 },
    { "timestamp": 1725661500, "count": 63 },
    { "timestamp": 1725661560, "count": 49 },
    { "timestamp": 1725661624, "count": 52 },
    { "timestamp": 1725661680, "count": 50 },
    { "timestamp": 1725661741, "count": 56 },
    { "timestamp": 1725661801, "count": 56 },
    { "timestamp": 1725661860, "count": 65 },
    { "timestamp": 1725661920, "count": 53 },
    { "timestamp": 1725661982, "count": 47 },
    { "timestamp": 1725662042, "count": 55 },
    { "timestamp": 1725662101, "count": 53 },
    { "timestamp": 1725662160, "count": 67 },
    { "timestamp": 1725662221, "count": 63 },
    { "timestamp": 1725662280, "count": 59 },
    { "timestamp": 1725662342, "count": 64 },
    { "timestamp": 1725662400, "count": 59 },
    { "timestamp": 1725662460, "count": 60 },
    { "timestamp": 1725662525, "count": 48 },
    { "timestamp": 1725662580, "count": 56 },
    { "timestamp": 1725662641, "count": 54 },
    { "timestamp": 1725662700, "count": 61 },
    { "timestamp": 1725662761, "count": 58 },
    { "timestamp": 1725662821, "count": 64 },
    { "timestamp": 1725662880, "count": 67 },
    { "timestamp": 1725662940, "count": 49 },
    { "timestamp": 1725663000, "count": 61 },
    { "timestamp": 1725663060, "count": 55 },
    { "timestamp": 1725663122, "count": 67 },
    { "timestamp": 1725663180, "count": 53 },
    { "timestamp": 1725663241, "count": 56 },
    { "timestamp": 1725663300, "count": 61 },
    { "timestamp": 1725663360, "count": 49 },
    { "timestamp": 1725663420, "count": 64 },
    { "timestamp": 1725663480, "count": 65 },
    { "timestamp": 1725663540, "count": 50 },
    { "timestamp": 1725663600, "count": 60 },
    { "timestamp": 1725663660, "count": 48 },
    { "timestamp": 1725663721, "count": 60 },
    { "timestamp": 1725663780, "count": 60 },
    { "timestamp": 1725663840, "count": 51 },
    { "timestamp": 1725663900, "count": 39 },
    { "timestamp": 1725663960, "count": 47 },
    { "timestamp": 1725664020, "count": 47 },
    { "timestamp": 1725664080, "count": 36 },
    { "timestamp": 1725664140, "count": 61 },
    { "timestamp": 1725664200, "count": 55 },
    { "timestamp": 1725664261, "count": 64 },
    { "timestamp": 1725664320, "count": 64 },
    { "timestamp": 1725664381, "count": 56 },
    { "timestamp": 1725664440, "count": 60 },
    { "timestamp": 1725664500, "count": 71 },
    { "timestamp": 1725664560, "count": 54 },
    { "timestamp": 1725664620, "count": 64 },
    { "timestamp": 1725664680, "count": 72 },
    { "timestamp": 1725664741, "count": 56 },
    { "timestamp": 1725664800, "count": 75 },
    { "timestamp": 1725664860, "count": 53 },
    { "timestamp": 1725664920, "count": 69 },
    { "timestamp": 1725664980, "count": 66 },
    { "timestamp": 1725665040, "count": 61 },
    { "timestamp": 1725665100, "count": 45 },
    { "timestamp": 1725665160, "count": 61 },
    { "timestamp": 1725665220, "count": 65 },
    { "timestamp": 1725665280, "count": 55 },
    { "timestamp": 1725665341, "count": 61 },
    { "timestamp": 1725665401, "count": 49 },
    { "timestamp": 1725665460, "count": 50 },
    { "timestamp": 1725665520, "count": 51 },
    { "timestamp": 1725665580, "count": 51 },
    { "timestamp": 1725665640, "count": 66 },
    { "timestamp": 1725665700, "count": 60 },
    { "timestamp": 1725665760, "count": 59 },
    { "timestamp": 1725665821, "count": 54 },
    { "timestamp": 1725665880, "count": 30 },
    { "timestamp": 1725665946, "count": 40 },
    { "timestamp": 1725666001, "count": 53 },
    { "timestamp": 1725666060, "count": 54 },
    { "timestamp": 1725666120, "count": 61 },
    { "timestamp": 1725666182, "count": 47 },
    { "timestamp": 1725666240, "count": 56 },
    { "timestamp": 1725666300, "count": 52 },
    { "timestamp": 1725666361, "count": 44 },
    { "timestamp": 1725666421, "count": 41 },
    { "timestamp": 1725666480, "count": 44 },
    { "timestamp": 1725666540, "count": 45 },
    { "timestamp": 1725666600, "count": 42 },
    { "timestamp": 1725666660, "count": 60 },
    { "timestamp": 1725666720, "count": 45 },
    { "timestamp": 1725666780, "count": 43 },
    { "timestamp": 1725666840, "count": 46 },
    { "timestamp": 1725666902, "count": 60 },
    { "timestamp": 1725666960, "count": 62 },
    { "timestamp": 1725667020, "count": 55 },
    { "timestamp": 1725667080, "count": 45 },
    { "timestamp": 1725667140, "count": 58 },
    { "timestamp": 1725667200, "count": 49 },
    { "timestamp": 1725667262, "count": 49 },
    { "timestamp": 1725667321, "count": 47 },
    { "timestamp": 1725667380, "count": 52 },
    { "timestamp": 1725667440, "count": 58 },
    { "timestamp": 1725667501, "count": 45 },
    { "timestamp": 1725667562, "count": 41 },
    { "timestamp": 1725667621, "count": 58 },
    { "timestamp": 1725667680, "count": 43 },
    { "timestamp": 1725667741, "count": 53 },
    { "timestamp": 1725667800, "count": 55 },
    { "timestamp": 1725667860, "count": 45 },
    { "timestamp": 1725667920, "count": 51 },
    { "timestamp": 1725667980, "count": 55 },
    { "timestamp": 1725668042, "count": 46 },
    { "timestamp": 1725668101, "count": 32 },
    { "timestamp": 1725668160, "count": 34 },
    { "timestamp": 1725668220, "count": 36 },
    { "timestamp": 1725668281, "count": 37 },
    { "timestamp": 1725668340, "count": 61 },
    { "timestamp": 1725668400, "count": 39 },
    { "timestamp": 1725668460, "count": 46 },
    { "timestamp": 1725668521, "count": 66 },
    { "timestamp": 1725668580, "count": 48 },
    { "timestamp": 1725668640, "count": 48 },
    { "timestamp": 1725668701, "count": 48 },
    { "timestamp": 1725668763, "count": 47 },
    { "timestamp": 1725668820, "count": 65 },
    { "timestamp": 1725668882, "count": 56 },
    { "timestamp": 1725668940, "count": 42 },
    { "timestamp": 1725669000, "count": 47 },
    { "timestamp": 1725669060, "count": 38 },
    { "timestamp": 1725669146, "count": 11 },
    { "timestamp": 1725669182, "count": 31 },
    { "timestamp": 1725669240, "count": 19 },
    { "timestamp": 1725669336, "count": 18 },
    { "timestamp": 1725669360, "count": 64 },
    { "timestamp": 1725669420, "count": 53 },
    { "timestamp": 1725669480, "count": 54 },
    { "timestamp": 1725669540, "count": 50 },
    { "timestamp": 1725669600, "count": 57 },
    { "timestamp": 1725669662, "count": 44 },
    { "timestamp": 1725669720, "count": 52 },
    { "timestamp": 1725669780, "count": 51 },
    { "timestamp": 1725669844, "count": 47 },
    { "timestamp": 1725669902, "count": 61 },
    { "timestamp": 1725669960, "count": 53 },
    { "timestamp": 1725670025, "count": 55 },
    { "timestamp": 1725670082, "count": 21 },
    { "timestamp": 1725670140, "count": 46 },
    { "timestamp": 1725670200, "count": 30 },
    { "timestamp": 1725670260, "count": 32 },
    { "timestamp": 1725670320, "count": 29 },
    { "timestamp": 1725670384, "count": 39 },
    { "timestamp": 1725670440, "count": 16 },
    { "timestamp": 1725670549, "count": 4 },
    { "timestamp": 1725670561, "count": 22 },
    { "timestamp": 1725670623, "count": 4 },
    { "timestamp": 1725723173, "count": 2 },
    { "timestamp": 1725724132, "count": 2 },
    { "timestamp": 1725724257, "count": 1 },
    { "timestamp": 1725724264, "count": 2 },
    { "timestamp": 1725727433, "count": 2 },
    { "timestamp": 1725727445, "count": 6 },
    { "timestamp": 1725727660, "count": 4 },
    { "timestamp": 1725727681, "count": 9 },
    { "timestamp": 1725728648, "count": 2 },
    { "timestamp": 1725728802, "count": 2 }
  ],
  "db_filename": "/tmp/db/cases.db",
  "start_timestamp": "09/05/2024 08:07:45",
  "stop_timestamp": "09/08/2024 08:09:20",
  "query_time": 0.042518069000038849,
  "errorCode": 0,
  "errorMessage": "Ok",
  "rows": 970
}
